complex_expr_parser/__init__.py
complex_expr_parser/_parser.py
complex_expr_parser/py.typed
complex_expr_parser-0.1.0.dist-info/METADATA
complex_expr_parser-0.1.0.dist-info/WHEEL
complex_expr_parser-0.1.0.dist-info/licenses/LICENSE
complex_expr_parser-0.1.0.dist-info/RECORD
