Metadata-Version: 2.4
Name: complex-expr-parser
Version: 0.1.0
Summary: A fault-tolerant parser for complex-valued mathematical functions with human-friendly notation support
Project-URL: Homepage, https://github.com/egoughnour/complex-expr-parser
Project-URL: Documentation, https://complex-expr-parser.readthedocs.io
Project-URL: Repository, https://github.com/egoughnour/complex-expr-parser
Project-URL: Issues, https://github.com/egoughnour/complex-expr-parser/issues
Author-email: Erik Goughnour <e.goughnour@gmail.com>
License-Expression: MIT
License-File: LICENSE
Keywords: complex,complex-analysis,functions,mathematics,parser,symbolic,sympy
Classifier: Development Status :: 4 - Beta
Classifier: Intended Audience :: Developers
Classifier: Intended Audience :: Science/Research
Classifier: License :: OSI Approved :: MIT License
Classifier: Operating System :: OS Independent
Classifier: Programming Language :: Python :: 3
Classifier: Programming Language :: Python :: 3.10
Classifier: Programming Language :: Python :: 3.11
Classifier: Programming Language :: Python :: 3.12
Classifier: Topic :: Scientific/Engineering :: Mathematics
Classifier: Topic :: Software Development :: Libraries :: Python Modules
Classifier: Typing :: Typed
Requires-Python: >=3.10
Requires-Dist: sympy>=1.12
Provides-Extra: all
Requires-Dist: mpmath>=1.3; extra == 'all'
Requires-Dist: numpy>=1.24; extra == 'all'
Provides-Extra: dev
Requires-Dist: mpmath>=1.3; extra == 'dev'
Requires-Dist: numpy>=1.24; extra == 'dev'
Requires-Dist: pytest-cov>=4.0; extra == 'dev'
Requires-Dist: pytest>=7.0; extra == 'dev'
Provides-Extra: docs
Requires-Dist: myst-parser>=2.0; extra == 'docs'
Requires-Dist: sphinx-rtd-theme>=2.0; extra == 'docs'
Requires-Dist: sphinx>=7.0; extra == 'docs'
Provides-Extra: mpmath
Requires-Dist: mpmath>=1.3; extra == 'mpmath'
Provides-Extra: numpy
Requires-Dist: numpy>=1.24; extra == 'numpy'
